jupyterlab_output_iframe/__init__.py
jupyterlab_output_iframe/_version.py
jupyterlab_output_iframe-0.1.1a0.data/data/share/jupyter/labextensions/jupyterlab_output_iframe/package.json
jupyterlab_output_iframe-0.1.1a0.data/data/share/jupyter/labextensions/jupyterlab_output_iframe/static/323.cd24065f623d444d95bd.js
jupyterlab_output_iframe-0.1.1a0.data/data/share/jupyter/labextensions/jupyterlab_output_iframe/static/728.2f881f4e354707f0573b.js
jupyterlab_output_iframe-0.1.1a0.data/data/share/jupyter/labextensions/jupyterlab_output_iframe/static/remoteEntry.d5c4882db710f350fa70.js
jupyterlab_output_iframe-0.1.1a0.data/data/share/jupyter/labextensions/jupyterlab_output_iframe/static/style.js
jupyterlab_output_iframe-0.1.1a0.data/data/share/jupyter/labextensions/jupyterlab_output_iframe/static/third-party-licenses.json
jupyterlab_output_iframe-0.1.1a0.data/data/share/jupyter/labextensions/jupyterlab_output_iframe/install.json
jupyterlab_output_iframe-0.1.1a0.dist-info/METADATA
jupyterlab_output_iframe-0.1.1a0.dist-info/WHEEL
jupyterlab_output_iframe-0.1.1a0.dist-info/licenses/LICENSE
jupyterlab_output_iframe-0.1.1a0.dist-info/RECORD
